LICENSE
MANIFEST.in
Makefile
README.rst
setup.py
doc/source/conf.py
doc/source/index.rst
doc/source/kit.rst
doc/source/pyprika.rst
doc/source/yaml-spec.rst
pyprika/__init__.py
pyprika/exceptions.py
pyprika/ingredient.py
pyprika/pprint.py
pyprika/quantity.py
pyprika/recipe.py
pyprika/version.py
pyprika.egg-info/PKG-INFO
pyprika.egg-info/SOURCES.txt
pyprika.egg-info/dependency_links.txt
pyprika.egg-info/entry_points.txt
pyprika.egg-info/requires.txt
pyprika.egg-info/top_level.txt
pyprika/kit/__init__.py
pyprika/kit/commands.py
pyprika/kit/main.py
pyprika/kit/registry.py
pyprika/tests/__init__.py
pyprika/tests/common.py
pyprika/tests/ingredient.py
pyprika/tests/main.py
pyprika/tests/quantity.py
pyprika/tests/recipe.py