Metadata-Version: 1.1
Name: pyprika
Version: 1.0.1
Summary: A recipe management library
Home-page: https://github.com/OEP/pyprika
Author: Paul Kilgo
Author-email: paulkilgo@gmail.com
License: UNKNOWN
Platform: UNKNOWN
Classifier: Intended Audience :: Developers
Classifier: Intended Audience :: End Users/Desktop
Classifier: License :: OSI Approved :: MIT License
Classifier: Operating System :: POSIX
Classifier: Programming Language :: Python
Classifier: Programming Language :: Python :: 2.7
Classifier: Topic :: Software Development :: Libraries :: Python Modules
Classifier: Topic :: Utilities
